trade_tui/__init__.py
trade_tui/__main__.py
trade_tui/menus/main_menu.py
trade_tui/menus/orderbook.py
trade_tui/menus/plots.py
trade_tui/menus/settings.py
trade_tui/util/backfill.py
trade_tui/util/banner.py
trade_tui/util/clear.py
trade_tui/util/colors.py
trade_tui/util/config.py
trade_tui/util/hex.py
trade_tui/util/indicators.py
trade_tui/util/input.py
trade_tui/util/types.py
trade_tui/util/ui.py
trade_tui-0.2.1.dist-info/WHEEL
trade_tui-0.2.1.dist-info/entry_points.txt
trade_tui-0.2.1.dist-info/METADATA
trade_tui-0.2.1.dist-info/RECORD
