Metadata-Version: 2.3
Name: trade-tui
Version: 0.2.1
Summary: A terminal-based crypto trading suite!
Author: xvcf
Author-email: xvcf <53903394+RafaeloxMC@users.noreply.github.com>
Requires-Dist: aiohttp
Requires-Dist: blessed
Requires-Dist: colorama
Requires-Dist: img2unicode[n2]
Requires-Dist: matplotlib==3.5.3
Requires-Dist: matplotlib-backend-kitty
Requires-Dist: matplotlib-terminal
Requires-Dist: websockets
Requires-Python: >=3.13
